asyncbots/__init__.py
asyncbots/bot.py
asyncbots/command.py
asyncbots/constants.py
asyncbots/events.py
asyncbots/history.py
asyncbots/ids.py
asyncbots/slack_api.py
asyncbots/util.py
asyncbots/parsing/__init__.py
asyncbots/parsing/slack_parser.py
asyncbots/parsing/symbols.py
asyncbots-0.1.8.dist-info/METADATA
asyncbots-0.1.8.dist-info/RECORD
asyncbots-0.1.8.dist-info/WHEEL
asyncbots-0.1.8.dist-info/top_level.txt
