Metadata-Version: 2.1
Name: asyncbots
Version: 0.1.8
Summary: A framework for Slack RTM bots.
Home-page: https://github.com/davisyoshida/asyncbots
Author: Davis Yoshida
Author-email: dyoshida@ttic.edu
License: MIT
Keywords: slack chatbot rtm bot
Platform: UNKNOWN
Classifier: Development Status :: 3 - Alpha
Classifier: Natural Language :: English
Classifier: License :: OSI Approved :: MIT License
Classifier: Intended Audience :: Developers
Classifier: Framework :: AsyncIO
Classifier: Operating System :: OS Independent
Classifier: Topic :: Software Development :: Libraries :: Python Modules
Requires-Python: >=3.5
Requires-Dist: mongoengine
Requires-Dist: pyparsing
Requires-Dist: requests
Requires-Dist: websockets
